ssl_metrics_meta/__init__.py
ssl_metrics_meta/main.py
ssl_metrics_meta/version.py
ssl_metrics_meta-0.8.dist-info/LICENSE
ssl_metrics_meta-0.8.dist-info/METADATA
ssl_metrics_meta-0.8.dist-info/WHEEL
ssl_metrics_meta-0.8.dist-info/top_level.txt
ssl_metrics_meta-0.8.dist-info/RECORD
