Metadata-Version: 2.1
Name: ssl-metrics-meta
Version: 0.8
Summary: SSL Metrics - Meta package to install all SoftwareSystemsLaboratory/ssl-metrics packages at once
Home-page: https://ssl.cs.luc.edu/projects/metricsDashboard
Author: Software and Systems Laboratory - Loyola University Chicago
Author-email: ssl-metrics@ssl.luc.edu
License: BSD
Project-URL: Bug Tracker, https://github.com/SoftwareSystemsLaboratory/ssl-metrics/issues
Project-URL: GitHub Repository, https://github.com/SoftwareSystemsLaboratory/ssl-metrics
Keywords: commits,engineering,git,github,kloc,loyola,loyola university chicago,luc,mining,metrics,repository,repository mining,simple,software,software engineering,software metrics,software systems laboratory,ssl
Platform: UNKNOWN
Classifier: Development Status :: 4 - Beta
Classifier: Intended Audience :: Science/Research
Classifier: Intended Audience :: Developers
Classifier: License :: OSI Approved :: BSD License
Classifier: Programming Language :: Python
Classifier: Programming Language :: Python :: 3
Classifier: Programming Language :: Python :: 3.9
Classifier: Programming Language :: Python :: 3 :: Only
Classifier: Topic :: Software Development
Classifier: Topic :: Scientific/Engineering
Classifier: Operating System :: POSIX
Classifier: Operating System :: Unix
Classifier: Operating System :: MacOS
Requires-Python: >=3.9
License-File: LICENSE
Requires-Dist: ssl-metrics-git-bus-factor
Requires-Dist: ssl-metrics-git-commits-loc
Requires-Dist: ssl-metrics-git-productivity
Requires-Dist: ssl-metrics-github-issues
Requires-Dist: ssl-metrics-github-issue-density
Requires-Dist: ssl-metrics-github-issue-spoilage
Requires-Dist: ssl-metrics-github-repository-searcher
Requires-Dist: ssl-metrics-json-converter
Requires-Dist: ssl-metrics-badges
